<?xml version="1.0" encoding="UTF-8"?>
<!DOCTYPE filesystem PUBLIC "-//NetBeans//DTD Filesystem 1.2//EN" "http://www.netbeans.org/dtds/filesystem-1_2.dtd">
<filesystem>
    <folder name="Actions">
        <folder name="Bucket">
            <file name="org-netbeans-modules-couchbase-bucket-queries-NoOfDisplayedDocumentsQuery-separatorBefore.instance">
                <attr name="instanceCreate" newvalue="javax.swing.JSeparator"/>
                <attr intvalue="50" name="position"/>
            </file>
            <file name="org-netbeans-modules-couchbase-bucket-queries-NoOfDisplayedDocumentsQuery.instance">
                <attr methodvalue="org.openide.awt.Actions.context" name="instanceCreate"/>
                <attr name="type" stringvalue="com.couchbase.client.java.Bucket"/>
                <attr methodvalue="org.openide.awt.Actions.inject" name="delegate"/>
                <attr name="injectable" stringvalue="org.netbeans.modules.couchbase.bucket.queries.NoOfDisplayedDocumentsQuery"/>
                <attr name="selectionType" stringvalue="EXACTLY_ONE"/>
                <attr name="displayName" stringvalue="Query: No. of Displayed Documents"/>
                <attr intvalue="60" name="position"/>
            </file>
            <file name="org-netbeans-modules-couchbase-bucket-queries-WhereDisplayedDocumentsQuery.instance">
                <attr methodvalue="org.openide.awt.Actions.context" name="instanceCreate"/>
                <attr name="type" stringvalue="com.couchbase.client.java.Bucket"/>
                <attr methodvalue="org.openide.awt.Actions.inject" name="delegate"/>
                <attr name="injectable" stringvalue="org.netbeans.modules.couchbase.bucket.queries.WhereDisplayedDocumentsQuery"/>
                <attr name="selectionType" stringvalue="EXACTLY_ONE"/>
                <attr name="displayName" stringvalue="Query: Where.../From..."/>
                <attr intvalue="70" name="position"/>
            </file>
        </folder>
    </folder>
</filesystem>
